mustash/__init__.py
mustash/core.py
mustash/es.py
mustash/exc.py
mustash/logstash.py
mustash/processors.py
mustash/py.typed
mustash/time.py
mustash/utils.py
mustash-0.3.dist-info/METADATA
mustash-0.3.dist-info/WHEEL
mustash-0.3.dist-info/RECORD
